fng_api/__init__.py
fng_api/main.py
fng_api-0.0.5.dist-info/LICENSE.txt
fng_api-0.0.5.dist-info/METADATA
fng_api-0.0.5.dist-info/WHEEL
fng_api-0.0.5.dist-info/top_level.txt
fng_api-0.0.5.dist-info/RECORD
