Metadata-Version: 2.1
Name: fng-api
Version: 0.0.5
Summary: API for fakenamegenerator.com
Home-page: https://github.com/TabulateJarl8/fng_api
Author: Tabulate
Author-email: tabulatejarl8@gmail.com
License: UNKNOWN
Platform: UNKNOWN
Classifier: Programming Language :: Python :: 3
Classifier: License :: OSI Approved :: MIT License
Classifier: Operating System :: OS Independent
Requires-Python: >=3.6
Requires-Dist: requests
Requires-Dist: bs4
